aegsum.py
aegsum-0.1.0.dist-info/METADATA
aegsum-0.1.0.dist-info/WHEEL
aegsum-0.1.0.dist-info/entry_points.txt
aegsum-0.1.0.dist-info/RECORD
