Metadata-Version: 2.4
Name: aegsum
Version: 0.1.0
Summary: CLI tool for incremental checksumming using AEGIS MAC.
Project-URL: Homepage, https://git.zi.fi/LeoVasanko/aegsum
Project-URL: Repository, https://github.com/LeoVasanko/aegsum
Author: Leo Vasanko
Keywords: AEGIS,MAC,checksum,cryptography
Classifier: Development Status :: 4 - Beta
Classifier: Environment :: Console
Classifier: Intended Audience :: Developers
Classifier: Intended Audience :: System Administrators
Classifier: Topic :: Security :: Cryptography
Classifier: Topic :: Utilities
Requires-Python: >=3.13
Requires-Dist: aeg>=0.4.3
Requires-Dist: base64url>=1.0.0
